ethopy/__init__.py
ethopy/cli.py
ethopy/config.py
ethopy/plugin_manager.py
ethopy/run.py
ethopy/setup_db.py
ethopy/behaviors/__init__.py
ethopy/behaviors/head_fixed.py
ethopy/behaviors/multi_port.py
ethopy/core/__init__.py
ethopy/core/behavior.py
ethopy/core/experiment.py
ethopy/core/interface.py
ethopy/core/logger.py
ethopy/core/recordings.py
ethopy/core/stimulus.py
ethopy/experiments/__init__.py
ethopy/experiments/calibrate.py
ethopy/experiments/free_water.py
ethopy/experiments/match_port.py
ethopy/experiments/passive.py
ethopy/interfaces/Arduino.py
ethopy/interfaces/Ball.py
ethopy/interfaces/Camera.py
ethopy/interfaces/DummyPorts.py
ethopy/interfaces/PCPorts.py
ethopy/interfaces/RPPorts.py
ethopy/interfaces/RPVR.py
ethopy/interfaces/__init__.py
ethopy/interfaces/dlc.py
ethopy/interfaces/arduino_firmware/README.md
ethopy/interfaces/arduino_firmware/arduino_digital_comm.ino
ethopy/interfaces/arduino_firmware/arduino_serial_comm.ino
ethopy/stimuli/__init__.py
ethopy/stimuli/bar.py
ethopy/stimuli/dot.py
ethopy/stimuli/grating.py
ethopy/task/bar_test.py
ethopy/task/calibrate_ports.py
ethopy/task/dot_test.py
ethopy/task/free_water.py
ethopy/task/grating_test.py
ethopy/task/no_stimulus.py
ethopy/utils/__init__.py
ethopy/utils/create_ethopy_task.py
ethopy/utils/ethopy_logging.py
ethopy/utils/exceptions.py
ethopy/utils/helper_functions.py
ethopy/utils/presenter.py
ethopy/utils/start.py
ethopy/utils/task.py
ethopy/utils/task_helper_funcs.py
ethopy/utils/thread_worker.py
ethopy/utils/timer.py
ethopy/utils/touch_interface.py
ethopy/utils/writer.py
ethopy/utils/export/nwb.py
ethopy/utils/plantuml/behavior.iuml
ethopy/utils/plantuml/experiments.iuml
ethopy/utils/plantuml/modules.iuml
ethopy/utils/plantuml/state_functions.iuml
ethopy/utils/plantuml/states.iuml
ethopy/utils/plantuml/stimuli.iuml
ethopy-0.0.8.7.dist-info/METADATA
ethopy-0.0.8.7.dist-info/WHEEL
ethopy-0.0.8.7.dist-info/entry_points.txt
ethopy-0.0.8.7.dist-info/licenses/LICENSE
ethopy-0.0.8.7.dist-info/RECORD
