Metadata-Version: 2.4
Name: ethopy
Version: 0.0.8.7
Summary: State control system for automated, high-throughput behavioral training.
Project-URL: Documentation, https://ef-lab.github.io/ethopy_package/
Project-URL: Repository, https://github.com/ef-lab/ethopy_package
Project-URL: Changelog, https://github.com/ef-lab/ethopy_package/releases
Author-email: Emmanouil Froudarakis <admin@example.com>, Alex Evangelou <evangelou.alexandr@gmail.com>
License: MIT License
License-File: LICENSE
Classifier: Development Status :: 3 - Alpha
Classifier: Intended Audience :: Developers
Classifier: License :: OSI Approved :: MIT License
Classifier: Natural Language :: English
Classifier: Programming Language :: Python :: 3.8
Classifier: Programming Language :: Python :: 3.9
Classifier: Programming Language :: Python :: 3.10
Classifier: Programming Language :: Python :: 3.11
Classifier: Typing :: Typed
Requires-Python: >=3.8
Requires-Dist: click>=8.1.0
Requires-Dist: datajoint
Requires-Dist: h5py
Requires-Dist: imageio
Requires-Dist: imageio-ffmpeg
Requires-Dist: numpy
Requires-Dist: pandas>=2.0.0
Requires-Dist: pyfiglet
Requires-Dist: pygame
Requires-Dist: pygame-menu
Requires-Dist: pynwb
Requires-Dist: pyopengl
Requires-Dist: scikit-learn>=1.3.2
Requires-Dist: scipy
Requires-Dist: setuptools>=75.3.0
Provides-Extra: dev
Requires-Dist: freezegun>=1.5.1; extra == 'dev'
Requires-Dist: isort>=5.0; extra == 'dev'
Requires-Dist: mypy>=1.0; extra == 'dev'
Requires-Dist: pytest-cov>=4.0; extra == 'dev'
Requires-Dist: pytest-mock>=3.14.0; extra == 'dev'
Requires-Dist: pytest>=7.0; extra == 'dev'
Requires-Dist: ruff>=0.0.290; extra == 'dev'
Provides-Extra: docs
Requires-Dist: mkdocs-jupyter; extra == 'docs'
Requires-Dist: mkdocs-material>=9.0.0; extra == 'docs'
Requires-Dist: mkdocs>=1.4.0; extra == 'docs'
Requires-Dist: mkdocstrings; extra == 'docs'
Requires-Dist: mkdocstrings-python>=1.11.1; extra == 'docs'
